pystospaboost/__init__.py
pystospaboost/pystospaboost.cpython-38-x86_64-linux-gnu.so
pystospaboost-2.0.19.dist-info/RECORD
pystospaboost-2.0.19.dist-info/WHEEL
pystospaboost-2.0.19.dist-info/METADATA
pystospaboost-2.0.19.dist-info/top_level.txt
pystospaboost-2.0.19.dist-info/LICENCE
